README.rst
setup.py
participation/__init__.py
participation.egg-info/PKG-INFO
participation.egg-info/SOURCES.txt
participation.egg-info/dependency_links.txt
participation.egg-info/top_level.txt