Metadata-Version: 1.1
Name: participation
Version: 0.1.dev1
Summary: Participation is a python package for social participation ontologies, rdf data (linked data) triplification and analysis
Home-page: https://github.com/ttm/participation
Author: Renato Fabbri
Author-email: listamacambira@googlegroups.com
License: MIT
Keywords: complexity networks human interaction physics data text mining analysis visualization music physics synthesis toolbox semantic web linked data owl ontology social participation
Platform: UNKNOWN
Classifier: Development Status :: 2 - Pre-Alpha
Classifier: Intended Audience :: Science/Research
Classifier: Intended Audience :: Developers
Classifier: Intended Audience :: Telecommunications Industry
Classifier: Intended Audience :: Education
Classifier: Intended Audience :: Religion
Classifier: Intended Audience :: Other Audience
Classifier: Topic :: Scientific/Engineering :: Physics
Classifier: Topic :: Scientific/Engineering :: Visualization
Classifier: Topic :: Scientific/Engineering :: Information Analysis
Classifier: Topic :: Multimedia :: Sound/Audio :: Sound Synthesis
Classifier: Topic :: Multimedia :: Sound/Audio :: Editors
Classifier: Topic :: Multimedia :: Sound/Audio :: Mixers
Classifier: Topic :: Multimedia :: Sound/Audio :: Speech
Classifier: Topic :: Artistic Software
Classifier: Topic :: Other/Nonlisted Topic
Classifier: Topic :: Text Processing
Classifier: Topic :: Text Processing :: Linguistic
Classifier: Topic :: Multimedia :: Graphics :: Presentation
Classifier: Topic :: Multimedia :: Sound/Audio :: Sound Synthesis
Classifier: Topic :: Multimedia :: Video :: Display
Classifier: License :: OSI Approved :: MIT License
Classifier: Programming Language :: Python :: 3
